{"ProdLineItemNum":"DMES-20240604-LFNEKG-ZGT","AssignmentID":"e3c69839-e4ba-45fb-8a89-3c2923022be5","ComponentSet":"OTHER, Pack M5/F9S/M5/F9S orange salmon (Pantone 150C), Spanish stamp, DD-tray, 10kit/bag, box 250,pass CAS","ProductType":0,"Products":[{"name":"ANY PRODUCT","description":null,"aliases":[],"family":{"name":"Datamars","description":"generic datamars product"},"business_line":3,"dimension":null,"shape":null,"identification_type":null,"electronic_type":null,"colors":[{"code":"0000","name":"NOT DEFINED"}],"image_url":"https://s3-eu-west-1.amazonaws.com/dm-ordering/public/img/upload/products/c3348483-c090-4c8f-a5d7-d31a10a04046.png"}],"Notes":"BOVINO\nU_ENDCUSTOMER: VILLAESCUSA S.A.\nU_CUSTORDER: UGV-84964\nU_REGA: ES192170000005","Colour":null,"NoOfItems":40,"AuthProperties":null,"OrderInformation":{"Address":"VILLAESCUSA, S.A. 2|667361625|C/  FRANCISCO SILVELA 93, OFICINA|28002 MADRID|Spain","Customer":"VILLAESCUSA, S.A."},"LfParameters":null,"UhfParameters":null,"LaserParameters":null,"ProdItems":[{"LineNumber":-1,"AuthCode":null,"AuthType":null,"Auth_retagging":0,"LFcode":null,"UHFcode":null,"keyCode":null,"LaserVars":null,"Lasers":[{"Disabled":false,"LaserType":4,"IsFront":true,"LayoutName":"DMESP_SK","LaserVars":[{"VarType":"CONSTANT","VarName":"LabelPeriod","VarValue":"100000"}]}],"Printers":null,"CustomVars":null},{"LineNumber":-1,"AuthCode":null,"AuthType":null,"Auth_retagging":0,"LFcode":null,"UHFcode":null,"keyCode":null,"LaserVars":null,"Lasers":[{"Disabled":false,"LaserType":4,"IsFront":true,"LayoutName":"DMESP_SK","LaserVars":[{"VarType":"CONSTANT","VarName":"LabelPeriod","VarValue":"100000"}]}],"Printers":null,"CustomVars":null},{"LineNumber":-1,"AuthCode":null,"AuthType":null,"Auth_retagging":0,"LFcode":null,"UHFcode":null,"keyCode":null,"LaserVars":null,"Lasers":[{"Disabled":false,"LaserType":4,"IsFront":true,"LayoutName":"DMESP_SK","LaserVars":[{"VarType":"CONSTANT","VarName":"LabelPeriod","VarValue":"100000"}]}],"Printers":null,"CustomVars":null},{"LineNumber":-1,"AuthCode":null,"AuthType":null,"Auth_retagging":0,"LFcode":null,"UHFcode":null,"keyCode":null,"LaserVars":null,"Lasers":[{"Disabled":false,"LaserType":4,"IsFront":true,"LayoutName":"DMESP_SK","LaserVars":[{"VarType":"CONSTANT","VarName":"LabelPeriod","VarValue":"100000"}]}],"Printers":null,"CustomVars":null},{"LineNumber":-1,"AuthCode":null,"AuthType":null,"Auth_retagging":0,"LFcode":null,"UHFcode":null,"keyCode":null,"LaserVars":null,"Lasers":[{"Disabled":false,"LaserType":4,"IsFront":true,"LayoutName":"DMESP_SK","LaserVars":[{"VarType":"CONSTANT","VarName":"LabelPeriod","VarValue":"100000"}]}],"Printers":null,"CustomVars":null},{"LineNumber":-1,"AuthCode":null,"AuthType":null,"Auth_retagging":0,"LFcode":null,"UHFcode":null,"keyCode":null,"LaserVars":null,"Lasers":[{"Disabled":false,"LaserType":4,"IsFront":true,"LayoutName":"DMESP_SK","LaserVars":[{"VarType":"CONSTANT","VarName":"LabelPeriod","VarValue":"100000"}]}],"Printers":null,"CustomVars":null},{"LineNumber":-1,"AuthCode":null,"AuthType":null,"Auth_retagging":0,"LFcode":null,"UHFcode":null,"keyCode":null,"LaserVars":null,"Lasers":[{"Disabled":false,"LaserType":4,"IsFront":true,"LayoutName":"DMESP_SK","LaserVars":[{"VarType":"CONSTANT","VarName":"LabelPeriod","VarValue":"100000"}]}],"Printers":null,"CustomVars":null},{"LineNumber":-1,"AuthCode":null,"AuthType":null,"Auth_retagging":0,"LFcode":null,"UHFcode":null,"keyCode":null,"LaserVars":null,"Lasers":[{"Disabled":false,"LaserType":4,"IsFront":true,"LayoutName":"DMESP_SK","LaserVars":[{"VarType":"CONSTANT","VarName":"LabelPeriod","VarValue":"100000"}]}],"Printers":null,"CustomVars":null},{"LineNumber":-1,"AuthCode":null,"AuthType":null,"Auth_retagging":0,"LFcode":null,"UHFcode":null,"keyCode":null,"LaserVars":null,"Lasers":[{"Disabled":false,"LaserType":4,"IsFront":true,"LayoutName":"DMESP_SK","LaserVars":[{"VarType":"CONSTANT","VarName":"LabelPeriod","VarValue":"100000"}]}],"Printers":null,"CustomVars":null},{"LineNumber":-1,"AuthCode":null,"AuthType":null,"Auth_retagging":0,"LFcode":null,"UHFcode":null,"keyCode":null,"LaserVars":null,"Lasers":[{"Disabled":false,"LaserType":4,"IsFront":true,"LayoutName":"DMESP_SK","LaserVars":[{"VarType":"CONSTANT","VarName":"LabelPeriod","VarValue":"100000"}]}],"Printers":null,"CustomVars":null},{"LineNumber":-1,"AuthCode":null,"AuthType":null,"Auth_retagging":0,"LFcode":null,"UHFcode":null,"keyCode":null,"LaserVars":null,"Lasers":[{"Disabled":false,"LaserType":4,"IsFront":true,"LayoutName":"DMESP_SK","LaserVars":[{"VarType":"CONSTANT","VarName":"LabelPeriod","VarValue":"100000"}]}],"Printers":null,"CustomVars":null},{"LineNumber":-1,"AuthCode":null,"AuthType":null,"Auth_retagging":0,"LFcode":null,"UHFcode":null,"keyCode":null,"LaserVars":null,"Lasers":[{"Disabled":false,"LaserType":4,"IsFront":true,"LayoutName":"DMESP_SK","LaserVars":[{"VarType":"CONSTANT","VarName":"LabelPeriod","VarValue":"100000"}]}],"Printers":null,"CustomVars":null},{"LineNumber":-1,"AuthCode":null,"AuthType":null,"Auth_retagging":0,"LFcode":null,"UHFcode":null,"keyCode":null,"LaserVars":null,"Lasers":[{"Disabled":false,"LaserType":4,"IsFront":true,"LayoutName":"DMESP_SK","LaserVars":[{"VarType":"CONSTANT","VarName":"LabelPeriod","VarValue":"100000"}]}],"Printers":null,"CustomVars":null},{"LineNumber":-1,"AuthCode":null,"AuthType":null,"Auth_retagging":0,"LFcode":null,"UHFcode":null,"keyCode":null,"LaserVars":null,"Lasers":[{"Disabled":false,"LaserType":4,"IsFront":true,"LayoutName":"DMESP_SK","LaserVars":[{"VarType":"CONSTANT","VarName":"LabelPeriod","VarValue":"100000"}]}],"Printers":null,"CustomVars":null},{"LineNumber":-1,"AuthCode":null,"AuthType":null,"Auth_retagging":0,"LFcode":null,"UHFcode":null,"keyCode":null,"LaserVars":null,"Lasers":[{"Disabled":false,"LaserType":4,"IsFront":true,"LayoutName":"DMESP_SK","LaserVars":[{"VarType":"CONSTANT","VarName":"LabelPeriod","VarValue":"100000"}]}],"Printers":null,"CustomVars":null},{"LineNumber":-1,"AuthCode":null,"AuthType":null,"Auth_retagging":0,"LFcode":null,"UHFcode":null,"keyCode":null,"LaserVars":null,"Lasers":[{"Disabled":false,"LaserType":4,"IsFront":true,"LayoutName":"DMESP_SK","LaserVars":[{"VarType":"CONSTANT","VarName":"LabelPeriod","VarValue":"100000"}]}],"Printers":null,"CustomVars":null},{"LineNumber":-1,"AuthCode":null,"AuthType":null,"Auth_retagging":0,"LFcode":null,"UHFcode":null,"keyCode":null,"LaserVars":null,"Lasers":[{"Disabled":false,"LaserType":4,"IsFront":true,"LayoutName":"DMESP_SK","LaserVars":[{"VarType":"CONSTANT","VarName":"LabelPeriod","VarValue":"100000"}]}],"Printers":null,"CustomVars":null},{"LineNumber":-1,"AuthCode":null,"AuthType":null,"Auth_retagging":0,"LFcode":null,"UHFcode":null,"keyCode":null,"LaserVars":null,"Lasers":[{"Disabled":false,"LaserType":4,"IsFront":true,"LayoutName":"DMESP_SK","LaserVars":[{"VarType":"CONSTANT","VarName":"LabelPeriod","VarValue":"100000"}]}],"Printers":null,"CustomVars":null},{"LineNumber":-1,"AuthCode":null,"AuthType":null,"Auth_retagging":0,"LFcode":null,"UHFcode":null,"keyCode":null,"LaserVars":null,"Lasers":[{"Disabled":false,"LaserType":4,"IsFront":true,"LayoutName":"DMESP_SK","LaserVars":[{"VarType":"CONSTANT","VarName":"LabelPeriod","VarValue":"100000"}]}],"Printers":null,"CustomVars":null},{"LineNumber":-1,"AuthCode":null,"AuthType":null,"Auth_retagging":0,"LFcode":null,"UHFcode":null,"keyCode":null,"LaserVars":null,"Lasers":[{"Disabled":false,"LaserType":4,"IsFront":true,"LayoutName":"DMESP_SK","LaserVars":[{"VarType":"CONSTANT","VarName":"LabelPeriod","VarValue":"100000"}]}],"Printers":null,"CustomVars":null},{"LineNumber":-1,"AuthCode":null,"AuthType":null,"Auth_retagging":0,"LFcode":null,"UHFcode":null,"keyCode":null,"LaserVars":null,"Lasers":[{"Disabled":false,"LaserType":4,"IsFront":true,"LayoutName":"DMESP_SK","LaserVars":[{"VarType":"CONSTANT","VarName":"LabelPeriod","VarValue":"100000"}]}],"Printers":null,"CustomVars":null},{"LineNumber":-1,"AuthCode":null,"AuthType":null,"Auth_retagging":0,"LFcode":null,"UHFcode":null,"keyCode":null,"LaserVars":null,"Lasers":[{"Disabled":false,"LaserType":4,"IsFront":true,"LayoutName":"DMESP_SK","LaserVars":[{"VarType":"CONSTANT","VarName":"LabelPeriod","VarValue":"100000"}]}],"Printers":null,"CustomVars":null},{"LineNumber":-1,"AuthCode":null,"AuthType":null,"Auth_retagging":0,"LFcode":null,"UHFcode":null,"keyCode":null,"LaserVars":null,"Lasers":[{"Disabled":false,"LaserType":4,"IsFront":true,"LayoutName":"DMESP_SK","LaserVars":[{"VarType":"CONSTANT","VarName":"LabelPeriod","VarValue":"100000"}]}],"Printers":null,"CustomVars":null},{"LineNumber":-1,"AuthCode":null,"AuthType":null,"Auth_retagging":0,"LFcode":null,"UHFcode":null,"keyCode":null,"LaserVars":null,"Lasers":[{"Disabled":false,"LaserType":4,"IsFront":true,"LayoutName":"DMESP_SK","LaserVars":[{"VarType":"CONSTANT","VarName":"LabelPeriod","VarValue":"100000"}]}],"Printers":null,"CustomVars":null},{"LineNumber":-1,"AuthCode":null,"AuthType":null,"Auth_retagging":0,"LFcode":null,"UHFcode":null,"keyCode":null,"LaserVars":null,"Lasers":[{"Disabled":false,"LaserType":4,"IsFront":true,"LayoutName":"DMESP_SK","LaserVars":[{"VarType":"CONSTANT","VarName":"LabelPeriod","VarValue":"100000"}]}],"Printers":null,"CustomVars":null},{"LineNumber":-1,"AuthCode":null,"AuthType":null,"Auth_retagging":0,"LFcode":null,"UHFcode":null,"keyCode":null,"LaserVars":null,"Lasers":[{"Disabled":false,"LaserType":4,"IsFront":true,"LayoutName":"DMESP_SK","LaserVars":[{"VarType":"CONSTANT","VarName":"LabelPeriod","VarValue":"100000"}]}],"Printers":null,"CustomVars":null},{"LineNumber":-1,"AuthCode":null,"AuthType":null,"Auth_retagging":0,"LFcode":null,"UHFcode":null,"keyCode":null,"LaserVars":null,"Lasers":[{"Disabled":false,"LaserType":4,"IsFront":true,"LayoutName":"DMESP_SK","LaserVars":[{"VarType":"CONSTANT","VarName":"LabelPeriod","VarValue":"100000"}]}],"Printers":null,"CustomVars":null},{"LineNumber":-1,"AuthCode":null,"AuthType":null,"Auth_retagging":0,"LFcode":null,"UHFcode":null,"keyCode":null,"LaserVars":null,"Lasers":[{"Disabled":false,"LaserType":4,"IsFront":true,"LayoutName":"DMESP_SK","LaserVars":[{"VarType":"CONSTANT","VarName":"LabelPeriod","VarValue":"100000"}]}],"Printers":null,"CustomVars":null},{"LineNumber":-1,"AuthCode":null,"AuthType":null,"Auth_retagging":0,"LFcode":null,"UHFcode":null,"keyCode":null,"LaserVars":null,"Lasers":[{"Disabled":false,"LaserType":4,"IsFront":true,"LayoutName":"DMESP_SK","LaserVars":[{"VarType":"CONSTANT","VarName":"LabelPeriod","VarValue":"100000"}]}],"Printers":null,"CustomVars":null},{"LineNumber":-1,"AuthCode":null,"AuthType":null,"Auth_retagging":0,"LFcode":null,"UHFcode":null,"keyCode":null,"LaserVars":null,"Lasers":[{"Disabled":false,"LaserType":4,"IsFront":true,"LayoutName":"DMESP_SK","LaserVars":[{"VarType":"CONSTANT","VarName":"LabelPeriod","VarValue":"100000"}]}],"Printers":null,"CustomVars":null},{"LineNumber":-1,"AuthCode":null,"AuthType":null,"Auth_retagging":0,"LFcode":null,"UHFcode":null,"keyCode":null,"LaserVars":null,"Lasers":[{"Disabled":false,"LaserType":4,"IsFront":true,"LayoutName":"DMESP_SK","LaserVars":[{"VarType":"CONSTANT","VarName":"LabelPeriod","VarValue":"100000"}]}],"Printers":null,"CustomVars":null},{"LineNumber":-1,"AuthCode":null,"AuthType":null,"Auth_retagging":0,"LFcode":null,"UHFcode":null,"keyCode":null,"LaserVars":null,"Lasers":[{"Disabled":false,"LaserType":4,"IsFront":true,"LayoutName":"DMESP_SK","LaserVars":[{"VarType":"CONSTANT","VarName":"LabelPeriod","VarValue":"100000"}]}],"Printers":null,"CustomVars":null},{"LineNumber":-1,"AuthCode":null,"AuthType":null,"Auth_retagging":0,"LFcode":null,"UHFcode":null,"keyCode":null,"LaserVars":null,"Lasers":[{"Disabled":false,"LaserType":4,"IsFront":true,"LayoutName":"DMESP_SK","LaserVars":[{"VarType":"CONSTANT","VarName":"LabelPeriod","VarValue":"100000"}]}],"Printers":null,"CustomVars":null},{"LineNumber":-1,"AuthCode":null,"AuthType":null,"Auth_retagging":0,"LFcode":null,"UHFcode":null,"keyCode":null,"LaserVars":null,"Lasers":[{"Disabled":false,"LaserType":4,"IsFront":true,"LayoutName":"DMESP_SK","LaserVars":[{"VarType":"CONSTANT","VarName":"LabelPeriod","VarValue":"100000"}]}],"Printers":null,"CustomVars":null},{"LineNumber":-1,"AuthCode":null,"AuthType":null,"Auth_retagging":0,"LFcode":null,"UHFcode":null,"keyCode":null,"LaserVars":null,"Lasers":[{"Disabled":false,"LaserType":4,"IsFront":true,"LayoutName":"DMESP_SK","LaserVars":[{"VarType":"CONSTANT","VarName":"LabelPeriod","VarValue":"100000"}]}],"Printers":null,"CustomVars":null},{"LineNumber":-1,"AuthCode":null,"AuthType":null,"Auth_retagging":0,"LFcode":null,"UHFcode":null,"keyCode":null,"LaserVars":null,"Lasers":[{"Disabled":false,"LaserType":4,"IsFront":true,"LayoutName":"DMESP_SK","LaserVars":[{"VarType":"CONSTANT","VarName":"LabelPeriod","VarValue":"100000"}]}],"Printers":null,"CustomVars":null},{"LineNumber":-1,"AuthCode":null,"AuthType":null,"Auth_retagging":0,"LFcode":null,"UHFcode":null,"keyCode":null,"LaserVars":null,"Lasers":[{"Disabled":false,"LaserType":4,"IsFront":true,"LayoutName":"DMESP_SK","LaserVars":[{"VarType":"CONSTANT","VarName":"LabelPeriod","VarValue":"100000"}]}],"Printers":null,"CustomVars":null},{"LineNumber":-1,"AuthCode":null,"AuthType":null,"Auth_retagging":0,"LFcode":null,"UHFcode":null,"keyCode":null,"LaserVars":null,"Lasers":[{"Disabled":false,"LaserType":4,"IsFront":true,"LayoutName":"DMESP_SK","LaserVars":[{"VarType":"CONSTANT","VarName":"LabelPeriod","VarValue":"100000"}]}],"Printers":null,"CustomVars":null},{"LineNumber":-1,"AuthCode":null,"AuthType":null,"Auth_retagging":0,"LFcode":null,"UHFcode":null,"keyCode":null,"LaserVars":null,"Lasers":[{"Disabled":false,"LaserType":4,"IsFront":true,"LayoutName":"DMESP_SK","LaserVars":[{"VarType":"CONSTANT","VarName":"LabelPeriod","VarValue":"100000"}]}],"Printers":null,"CustomVars":null},{"LineNumber":-1,"AuthCode":null,"AuthType":null,"Auth_retagging":0,"LFcode":null,"UHFcode":null,"keyCode":null,"LaserVars":null,"Lasers":[{"Disabled":false,"LaserType":4,"IsFront":true,"LayoutName":"DMESP_SK","LaserVars":[{"VarType":"CONSTANT","VarName":"LabelPeriod","VarValue":"100000"}]}],"Printers":null,"CustomVars":null}]}